{
  "date": "2026-06-21",
  "updated": "2026-06-21T15:00:30.173112Z",
  "predictions": [
    {
      "game_time": "1:35 PM ET",
      "away_team": "Cincinnati Reds",
      "home_team": "New York Yankees",
      "away_sp": "Chase Burns",
      "home_sp": "Elmer Rodr\u00edguez",
      "away_prob": 0.4321,
      "home_prob": 0.5679,
      "pick": "New York Yankees",
      "confidence": 0.5679,
      "actual_winner": null,
      "correct": null
    },
    {
      "game_time": "1:35 PM ET",
      "away_team": "Milwaukee Brewers",
      "home_team": "Atlanta Braves",
      "away_sp": "Robert Gasser",
      "home_sp": "Bryce Elder",
      "away_prob": 0.4175,
      "home_prob": 0.5825,
      "pick": "Atlanta Braves",
      "confidence": 0.5825,
      "actual_winner": null,
      "correct": null
    },
    {
      "game_time": "1:40 PM ET",
      "away_team": "Washington Nationals",
      "home_team": "Tampa Bay Rays",
      "away_sp": "Andrew Alvarez",
      "home_sp": "Nick Martinez",
      "away_prob": 0.4615,
      "home_prob": 0.5385,
      "pick": "Tampa Bay Rays",
      "confidence": 0.5385,
      "actual_winner": null,
      "correct": null
    },
    {
      "game_time": "1:40 PM ET",
      "away_team": "Chicago White Sox",
      "home_team": "Detroit Tigers",
      "away_sp": "Davis Martin",
      "home_sp": "Keider Montero",
      "away_prob": 0.5042,
      "home_prob": 0.4958,
      "pick": "Chicago White Sox",
      "confidence": 0.5042,
      "actual_winner": null,
      "correct": null
    },
    {
      "game_time": "1:40 PM ET",
      "away_team": "San Francisco Giants",
      "home_team": "Miami Marlins",
      "away_sp": "Logan Webb",
      "home_sp": "Ryan Gusto",
      "away_prob": 0.5314,
      "home_prob": 0.4686,
      "pick": "San Francisco Giants",
      "confidence": 0.5314,
      "actual_winner": null,
      "correct": null
    },
    {
      "game_time": "2:10 PM ET",
      "away_team": "Cleveland Guardians",
      "home_team": "Houston Astros",
      "away_sp": "Slade Cecconi",
      "home_sp": "Kai-Wei Teng",
      "away_prob": 0.4853,
      "home_prob": 0.5147,
      "pick": "Houston Astros",
      "confidence": 0.5147,
      "actual_winner": null,
      "correct": null
    },
    {
      "game_time": "2:10 PM ET",
      "away_team": "St. Louis Cardinals",
      "home_team": "Kansas City Royals",
      "away_sp": "Dustin May",
      "home_sp": "Stephen Kolek",
      "away_prob": 0.5119,
      "home_prob": 0.4881,
      "pick": "St. Louis Cardinals",
      "confidence": 0.5119,
      "actual_winner": null,
      "correct": null
    },
    {
      "game_time": "2:20 PM ET",
      "away_team": "Toronto Blue Jays",
      "home_team": "Chicago Cubs",
      "away_sp": "Dylan Cease",
      "home_sp": "Shota Imanaga",
      "away_prob": 0.5451,
      "home_prob": 0.4549,
      "pick": "Toronto Blue Jays",
      "confidence": 0.5451,
      "actual_winner": null,
      "correct": null
    },
    {
      "game_time": "2:35 PM ET",
      "away_team": "San Diego Padres",
      "home_team": "Texas Rangers",
      "away_sp": "Wandy Peralta",
      "home_sp": "Nathan Eovaldi",
      "away_prob": 0.5276,
      "home_prob": 0.4724,
      "pick": "San Diego Padres",
      "confidence": 0.5276,
      "actual_winner": null,
      "correct": null
    },
    {
      "game_time": "3:10 PM ET",
      "away_team": "Pittsburgh Pirates",
      "home_team": "Colorado Rockies",
      "away_sp": "Jared Jones",
      "home_sp": "Michael Lorenzen",
      "away_prob": 0.571,
      "home_prob": 0.429,
      "pick": "Pittsburgh Pirates",
      "confidence": 0.571,
      "actual_winner": null,
      "correct": null
    },
    {
      "game_time": "3:15 PM ET",
      "away_team": "Minnesota Twins",
      "home_team": "Arizona Diamondbacks",
      "away_sp": "Mike Paredes",
      "home_sp": "Jose Cabrera",
      "away_prob": 0.4829,
      "home_prob": 0.5171,
      "pick": "Arizona Diamondbacks",
      "confidence": 0.5171,
      "actual_winner": null,
      "correct": null
    },
    {
      "game_time": "4:05 PM ET",
      "away_team": "Los Angeles Angels",
      "home_team": "Athletics",
      "away_sp": "Reid Detmers",
      "home_sp": "Jack Perkins",
      "away_prob": 0.5402,
      "home_prob": 0.4598,
      "pick": "Los Angeles Angels",
      "confidence": 0.5402,
      "actual_winner": null,
      "correct": null
    },
    {
      "game_time": "4:10 PM ET",
      "away_team": "Baltimore Orioles",
      "home_team": "Los Angeles Dodgers",
      "away_sp": "Brandon Young",
      "home_sp": "Emmet Sheehan",
      "away_prob": 0.4046,
      "home_prob": 0.5954,
      "pick": "Los Angeles Dodgers",
      "confidence": 0.5954,
      "actual_winner": null,
      "correct": null
    },
    {
      "game_time": "4:10 PM ET",
      "away_team": "Boston Red Sox",
      "home_team": "Seattle Mariners",
      "away_sp": "Payton Tolle",
      "home_sp": "Logan Gilbert",
      "away_prob": 0.4283,
      "home_prob": 0.5717,
      "pick": "Seattle Mariners",
      "confidence": 0.5717,
      "actual_winner": null,
      "correct": null
    },
    {
      "game_time": "7:20 PM ET",
      "away_team": "New York Mets",
      "home_team": "Philadelphia Phillies",
      "away_sp": "David Peterson",
      "home_sp": "Zack Wheeler",
      "away_prob": 0.4182,
      "home_prob": 0.5818,
      "pick": "Philadelphia Phillies",
      "confidence": 0.5818,
      "actual_winner": null,
      "correct": null
    }
  ],
  "yesterday": {
    "total": {
      "wins": 7,
      "losses": 7,
      "total": 14
    },
    "by_confidence": [
      {
        "band": "50\u201355%",
        "wins": 5,
        "losses": 3,
        "total": 8
      },
      {
        "band": "55\u201360%",
        "wins": 2,
        "losses": 2,
        "total": 4
      },
      {
        "band": "60\u201365%",
        "wins": 0,
        "losses": 1,
        "total": 1
      },
      {
        "band": "65\u201370%",
        "wins": 0,
        "losses": 1,
        "total": 1
      },
      {
        "band": "70\u201375%",
        "wins": 0,
        "losses": 0,
        "total": 0
      },
      {
        "band": "75\u201380%",
        "wins": 0,
        "losses": 0,
        "total": 0
      },
      {
        "band": "80%+",
        "wins": 0,
        "losses": 0,
        "total": 0
      }
    ],
    "date": "2026-06-20"
  },
  "alltime": {
    "total": {
      "wins": 307,
      "losses": 236,
      "total": 543
    },
    "by_confidence": [
      {
        "band": "50\u201355%",
        "wins": 202,
        "losses": 160,
        "total": 362
      },
      {
        "band": "55\u201360%",
        "wins": 77,
        "losses": 62,
        "total": 139
      },
      {
        "band": "60\u201365%",
        "wins": 24,
        "losses": 13,
        "total": 37
      },
      {
        "band": "65\u201370%",
        "wins": 4,
        "losses": 1,
        "total": 5
      },
      {
        "band": "70\u201375%",
        "wins": 0,
        "losses": 0,
        "total": 0
      },
      {
        "band": "75\u201380%",
        "wins": 0,
        "losses": 0,
        "total": 0
      },
      {
        "band": "80%+",
        "wins": 0,
        "losses": 0,
        "total": 0
      }
    ]
  }
}