{
  "records": [
    {
      "date": "2026-05-12",
      "games": [
        {
          "game_time": "6:10 PM ET",
          "away_team": "Los Angeles Angels",
          "home_team": "Cleveland Guardians",
          "away_pct": 0.381,
          "home_pct": 0.512,
          "away_prob": 0.35,
          "home_prob": 0.65,
          "pick": "Cleveland Guardians",
          "confidence": 0.65,
          "actual_winner": null,
          "correct": null
        },
        {
          "game_time": "6:35 PM ET",
          "away_team": "New York Yankees",
          "home_team": "Baltimore Orioles",
          "away_pct": 0.619,
          "home_pct": 0.452,
          "away_prob": 0.643,
          "home_prob": 0.357,
          "pick": "New York Yankees",
          "confidence": 0.643,
          "actual_winner": null,
          "correct": null
        },
        {
          "game_time": "6:40 PM ET",
          "away_team": "Washington Nationals",
          "home_team": "Cincinnati Reds",
          "away_pct": 0.463,
          "home_pct": 0.537,
          "away_prob": 0.4072,
          "home_prob": 0.5928,
          "pick": "Cincinnati Reds",
          "confidence": 0.5928,
          "actual_winner": null,
          "correct": null
        },
        {
          "game_time": "6:40 PM ET",
          "away_team": "Colorado Rockies",
          "home_team": "Pittsburgh Pirates",
          "away_pct": 0.39,
          "home_pct": 0.537,
          "away_prob": 0.336,
          "home_prob": 0.664,
          "pick": "Pittsburgh Pirates",
          "confidence": 0.664,
          "actual_winner": null,
          "correct": null
        },
        {
          "game_time": "6:45 PM ET",
          "away_team": "Philadelphia Phillies",
          "home_team": "Boston Red Sox",
          "away_pct": 0.463,
          "home_pct": 0.425,
          "away_prob": 0.5188,
          "home_prob": 0.4812,
          "pick": "Philadelphia Phillies",
          "confidence": 0.5188,
          "actual_winner": null,
          "correct": null
        },
        {
          "game_time": "7:07 PM ET",
          "away_team": "Tampa Bay Rays",
          "home_team": "Toronto Blue Jays",
          "away_pct": 0.675,
          "home_pct": 0.439,
          "away_prob": 0.7063,
          "home_prob": 0.2937,
          "pick": "Tampa Bay Rays",
          "confidence": 0.7063,
          "actual_winner": null,
          "correct": null
        },
        {
          "game_time": "7:10 PM ET",
          "away_team": "Detroit Tigers",
          "home_team": "New York Mets",
          "away_pct": 0.463,
          "home_pct": 0.375,
          "away_prob": 0.5701,
          "home_prob": 0.4299,
          "pick": "Detroit Tigers",
          "confidence": 0.5701,
          "actual_winner": null,
          "correct": null
        },
        {
          "game_time": "7:15 PM ET",
          "away_team": "Chicago Cubs",
          "home_team": "Atlanta Braves",
          "away_pct": 0.659,
          "home_pct": 0.683,
          "away_prob": 0.4524,
          "home_prob": 0.5476,
          "pick": "Atlanta Braves",
          "confidence": 0.5476,
          "actual_winner": null,
          "correct": null
        },
        {
          "game_time": "7:40 PM ET",
          "away_team": "Kansas City Royals",
          "home_team": "Chicago White Sox",
          "away_pct": 0.463,
          "home_pct": 0.475,
          "away_prob": 0.4684,
          "home_prob": 0.5316,
          "pick": "Chicago White Sox",
          "confidence": 0.5316,
          "actual_winner": null,
          "correct": null
        },
        {
          "game_time": "7:40 PM ET",
          "away_team": "Miami Marlins",
          "home_team": "Minnesota Twins",
          "away_pct": 0.463,
          "home_pct": 0.439,
          "away_prob": 0.5046,
          "home_prob": 0.4954,
          "pick": "Miami Marlins",
          "confidence": 0.5046,
          "actual_winner": null,
          "correct": null
        },
        {
          "game_time": "7:40 PM ET",
          "away_team": "San Diego Padres",
          "home_team": "Milwaukee Brewers",
          "away_pct": 0.6,
          "home_pct": 0.579,
          "away_prob": 0.5017,
          "home_prob": 0.4983,
          "pick": "San Diego Padres",
          "confidence": 0.5017,
          "actual_winner": null,
          "correct": null
        },
        {
          "game_time": "8:05 PM ET",
          "away_team": "Arizona Diamondbacks",
          "home_team": "Texas Rangers",
          "away_pct": 0.5,
          "home_pct": 0.463,
          "away_prob": 0.5166,
          "home_prob": 0.4834,
          "pick": "Arizona Diamondbacks",
          "confidence": 0.5166,
          "actual_winner": null,
          "correct": null
        },
        {
          "game_time": "8:10 PM ET",
          "away_team": "Seattle Mariners",
          "home_team": "Houston Astros",
          "away_pct": 0.476,
          "home_pct": 0.381,
          "away_prob": 0.5763,
          "home_prob": 0.4237,
          "pick": "Seattle Mariners",
          "confidence": 0.5763,
          "actual_winner": null,
          "correct": null
        },
        {
          "game_time": "9:40 PM ET",
          "away_team": "St. Louis Cardinals",
          "home_team": "Athletics",
          "away_pct": 0.575,
          "home_pct": 0.525,
          "away_prob": 0.5304,
          "home_prob": 0.4696,
          "pick": "St. Louis Cardinals",
          "confidence": 0.5304,
          "actual_winner": null,
          "correct": null
        },
        {
          "game_time": "10:10 PM ET",
          "away_team": "San Francisco Giants",
          "home_team": "Los Angeles Dodgers",
          "away_pct": 0.415,
          "home_pct": 0.585,
          "away_prob": 0.3141,
          "home_prob": 0.6859,
          "pick": "Los Angeles Dodgers",
          "confidence": 0.6859,
          "actual_winner": null,
          "correct": null
        }
      ]
    },
    {
      "date": "2026-05-11",
      "games": [
        {
          "game_time": "6:10 PM ET",
          "away_team": "Los Angeles Angels",
          "home_team": "Cleveland Guardians",
          "away_pct": 0.39,
          "home_pct": 0.5,
          "away_prob": 0.3702,
          "home_prob": 0.6298,
          "pick": "Cleveland Guardians",
          "confidence": 0.6298,
          "actual_winner": "Cleveland Guardians",
          "correct": true
        },
        {
          "game_time": "6:35 PM ET",
          "away_team": "New York Yankees",
          "home_team": "Baltimore Orioles",
          "away_pct": 0.634,
          "home_pct": 0.439,
          "away_prob": 0.6689,
          "home_prob": 0.3311,
          "pick": "New York Yankees",
          "confidence": 0.6689,
          "actual_winner": "Baltimore Orioles",
          "correct": false
        },
        {
          "game_time": "7:07 PM ET",
          "away_team": "Tampa Bay Rays",
          "home_team": "Toronto Blue Jays",
          "away_pct": 0.667,
          "home_pct": 0.45,
          "away_prob": 0.6897,
          "home_prob": 0.3103,
          "pick": "Tampa Bay Rays",
          "confidence": 0.6897,
          "actual_winner": "Tampa Bay Rays",
          "correct": true
        },
        {
          "game_time": "8:05 PM ET",
          "away_team": "Arizona Diamondbacks",
          "home_team": "Texas Rangers",
          "away_pct": 0.487,
          "home_pct": 0.475,
          "away_prob": 0.4922,
          "home_prob": 0.5078,
          "pick": "Texas Rangers",
          "confidence": 0.5078,
          "actual_winner": "Arizona Diamondbacks",
          "correct": false
        },
        {
          "game_time": "8:10 PM ET",
          "away_team": "Seattle Mariners",
          "home_team": "Houston Astros",
          "away_pct": 0.463,
          "home_pct": 0.39,
          "away_prob": 0.5544,
          "home_prob": 0.4456,
          "pick": "Seattle Mariners",
          "confidence": 0.5544,
          "actual_winner": "Seattle Mariners",
          "correct": true
        },
        {
          "game_time": "10:10 PM ET",
          "away_team": "San Francisco Giants",
          "home_team": "Los Angeles Dodgers",
          "away_pct": 0.4,
          "home_pct": 0.6,
          "away_prob": 0.2877,
          "home_prob": 0.7123,
          "pick": "Los Angeles Dodgers",
          "confidence": 0.7123,
          "actual_winner": "San Francisco Giants",
          "correct": false
        }
      ]
    },
    {
      "date": "2026-05-10",
      "games": [
        {
          "game_time": "12:15 PM ET",
          "away_team": "Washington Nationals",
          "home_team": "Miami Marlins",
          "away_pct": 0.475,
          "home_pct": 0.45,
          "away_prob": 0.5051,
          "home_prob": 0.4949,
          "pick": "Washington Nationals",
          "confidence": 0.5051,
          "actual_winner": "Miami Marlins",
          "correct": false
        },
        {
          "game_time": "1:35 PM ET",
          "away_team": "Athletics",
          "home_team": "Baltimore Orioles",
          "away_pct": 0.538,
          "home_pct": 0.425,
          "away_prob": 0.5922,
          "home_prob": 0.4078,
          "pick": "Athletics",
          "confidence": 0.5922,
          "actual_winner": "Baltimore Orioles",
          "correct": false
        },
        {
          "game_time": "1:35 PM ET",
          "away_team": "Tampa Bay Rays",
          "home_team": "Boston Red Sox",
          "away_pct": 0.658,
          "home_pct": 0.436,
          "away_prob": 0.6934,
          "home_prob": 0.3066,
          "pick": "Tampa Bay Rays",
          "confidence": 0.6934,
          "actual_winner": "Tampa Bay Rays",
          "correct": true
        },
        {
          "game_time": "1:35 PM ET",
          "away_team": "Colorado Rockies",
          "home_team": "Philadelphia Phillies",
          "away_pct": 0.4,
          "home_pct": 0.45,
          "away_prob": 0.429,
          "home_prob": 0.571,
          "pick": "Philadelphia Phillies",
          "confidence": 0.571,
          "actual_winner": "Philadelphia Phillies",
          "correct": true
        },
        {
          "game_time": "1:37 PM ET",
          "away_team": "Los Angeles Angels",
          "home_team": "Toronto Blue Jays",
          "away_pct": 0.375,
          "home_pct": 0.462,
          "away_prob": 0.3918,
          "home_prob": 0.6082,
          "pick": "Toronto Blue Jays",
          "confidence": 0.6082,
          "actual_winner": "Los Angeles Angels",
          "correct": false
        },
        {
          "game_time": "1:40 PM ET",
          "away_team": "Houston Astros",
          "home_team": "Cincinnati Reds",
          "away_pct": 0.4,
          "home_pct": 0.525,
          "away_prob": 0.3562,
          "home_prob": 0.6438,
          "pick": "Cincinnati Reds",
          "confidence": 0.6438,
          "actual_winner": "Cincinnati Reds",
          "correct": true
        },
        {
          "game_time": "1:40 PM ET",
          "away_team": "Minnesota Twins",
          "home_team": "Cleveland Guardians",
          "away_pct": 0.425,
          "home_pct": 0.512,
          "away_prob": 0.3931,
          "home_prob": 0.6069,
          "pick": "Cleveland Guardians",
          "confidence": 0.6069,
          "actual_winner": "Minnesota Twins",
          "correct": false
        },
        {
          "game_time": "2:10 PM ET",
          "away_team": "Seattle Mariners",
          "home_team": "Chicago White Sox",
          "away_pct": 0.475,
          "home_pct": 0.462,
          "away_prob": 0.4935,
          "home_prob": 0.5065,
          "pick": "Chicago White Sox",
          "confidence": 0.5065,
          "actual_winner": "Chicago White Sox",
          "correct": true
        },
        {
          "game_time": "2:10 PM ET",
          "away_team": "New York Yankees",
          "home_team": "Milwaukee Brewers",
          "away_pct": 0.65,
          "home_pct": 0.568,
          "away_prob": 0.5659,
          "home_prob": 0.4341,
          "pick": "New York Yankees",
          "confidence": 0.5659,
          "actual_winner": "Milwaukee Brewers",
          "correct": false
        },
        {
          "game_time": "2:35 PM ET",
          "away_team": "Chicago Cubs",
          "home_team": "Texas Rangers",
          "away_pct": 0.675,
          "home_pct": 0.462,
          "away_prob": 0.6879,
          "home_prob": 0.3121,
          "pick": "Chicago Cubs",
          "confidence": 0.6879,
          "actual_winner": "Texas Rangers",
          "correct": false
        },
        {
          "game_time": "4:05 PM ET",
          "away_team": "Pittsburgh Pirates",
          "home_team": "San Francisco Giants",
          "away_pct": 0.55,
          "home_pct": 0.385,
          "away_prob": 0.6417,
          "home_prob": 0.3583,
          "pick": "Pittsburgh Pirates",
          "confidence": 0.6417,
          "actual_winner": "San Francisco Giants",
          "correct": false
        },
        {
          "game_time": "4:10 PM ET",
          "away_team": "New York Mets",
          "home_team": "Arizona Diamondbacks",
          "away_pct": 0.385,
          "home_pct": 0.474,
          "away_prob": 0.3898,
          "home_prob": 0.6102,
          "pick": "Arizona Diamondbacks",
          "confidence": 0.6102,
          "actual_winner": "Arizona Diamondbacks",
          "correct": true
        },
        {
          "game_time": "4:10 PM ET",
          "away_team": "St. Louis Cardinals",
          "home_team": "San Diego Padres",
          "away_pct": 0.59,
          "home_pct": 0.59,
          "away_prob": 0.48,
          "home_prob": 0.52,
          "pick": "San Diego Padres",
          "confidence": 0.52,
          "actual_winner": "San Diego Padres",
          "correct": true
        },
        {
          "game_time": "4:10 PM ET",
          "away_team": "Atlanta Braves",
          "home_team": "Los Angeles Dodgers",
          "away_pct": 0.675,
          "home_pct": 0.615,
          "away_prob": 0.5449,
          "home_prob": 0.4551,
          "pick": "Atlanta Braves",
          "confidence": 0.5449,
          "actual_winner": "Atlanta Braves",
          "correct": true
        },
        {
          "game_time": "7:20 PM ET",
          "away_team": "Detroit Tigers",
          "home_team": "Kansas City Royals",
          "away_pct": 0.45,
          "home_pct": 0.475,
          "away_prob": 0.4549,
          "home_prob": 0.5451,
          "pick": "Kansas City Royals",
          "confidence": 0.5451,
          "actual_winner": "Detroit Tigers",
          "correct": false
        }
      ]
    },
    {
      "date": "2026-05-09",
      "games": [
        {
          "game_time": "3:07 PM ET",
          "away_team": "Los Angeles Angels",
          "home_team": "Toronto Blue Jays",
          "away_pct": 0.375,
          "home_pct": 0.462,
          "away_prob": 0.3918,
          "home_prob": 0.6082,
          "pick": "Toronto Blue Jays",
          "confidence": 0.6082,
          "actual_winner": "Toronto Blue Jays",
          "correct": true
        },
        {
          "game_time": "4:05 PM ET",
          "away_team": "Athletics",
          "home_team": "Baltimore Orioles",
          "away_pct": 0.538,
          "home_pct": 0.425,
          "away_prob": 0.5922,
          "home_prob": 0.4078,
          "pick": "Athletics",
          "confidence": 0.5922,
          "actual_winner": "Athletics",
          "correct": true
        },
        {
          "game_time": "4:10 PM ET",
          "away_team": "Houston Astros",
          "home_team": "Cincinnati Reds",
          "away_pct": 0.4,
          "home_pct": 0.525,
          "away_prob": 0.3562,
          "home_prob": 0.6438,
          "pick": "Cincinnati Reds",
          "confidence": 0.6438,
          "actual_winner": "Cincinnati Reds",
          "correct": true
        },
        {
          "game_time": "4:10 PM ET",
          "away_team": "Washington Nationals",
          "home_team": "Miami Marlins",
          "away_pct": 0.487,
          "home_pct": 0.436,
          "away_prob": 0.5315,
          "home_prob": 0.4685,
          "pick": "Washington Nationals",
          "confidence": 0.5315,
          "actual_winner": "Miami Marlins",
          "correct": false
        },
        {
          "game_time": "6:05 PM ET",
          "away_team": "Colorado Rockies",
          "home_team": "Philadelphia Phillies",
          "away_pct": 0.41,
          "home_pct": 0.436,
          "away_prob": 0.4538,
          "home_prob": 0.5462,
          "pick": "Philadelphia Phillies",
          "confidence": 0.5462,
          "actual_winner": "Philadelphia Phillies",
          "correct": true
        },
        {
          "game_time": "6:10 PM ET",
          "away_team": "Minnesota Twins",
          "home_team": "Cleveland Guardians",
          "away_pct": 0.41,
          "home_pct": 0.525,
          "away_prob": 0.3663,
          "home_prob": 0.6337,
          "pick": "Cleveland Guardians",
          "confidence": 0.6337,
          "actual_winner": "Minnesota Twins",
          "correct": false
        },
        {
          "game_time": "7:05 PM ET",
          "away_team": "Chicago Cubs",
          "home_team": "Texas Rangers",
          "away_pct": 0.692,
          "home_pct": 0.447,
          "away_prob": 0.7154,
          "home_prob": 0.2846,
          "pick": "Chicago Cubs",
          "confidence": 0.7154,
          "actual_winner": "Texas Rangers",
          "correct": false
        },
        {
          "game_time": "7:10 PM ET",
          "away_team": "Detroit Tigers",
          "home_team": "Kansas City Royals",
          "away_pct": 0.462,
          "home_pct": 0.462,
          "away_prob": 0.48,
          "home_prob": 0.52,
          "pick": "Kansas City Royals",
          "confidence": 0.52,
          "actual_winner": "Kansas City Royals",
          "correct": true
        },
        {
          "game_time": "7:10 PM ET",
          "away_team": "Seattle Mariners",
          "home_team": "Chicago White Sox",
          "away_pct": 0.487,
          "home_pct": 0.447,
          "away_prob": 0.5199,
          "home_prob": 0.4801,
          "pick": "Seattle Mariners",
          "confidence": 0.5199,
          "actual_winner": "Chicago White Sox",
          "correct": false
        },
        {
          "game_time": "7:10 PM ET",
          "away_team": "New York Yankees",
          "home_team": "Milwaukee Brewers",
          "away_pct": 0.667,
          "home_pct": 0.556,
          "away_prob": 0.5954,
          "home_prob": 0.4046,
          "pick": "New York Yankees",
          "confidence": 0.5954,
          "actual_winner": "Milwaukee Brewers",
          "correct": false
        },
        {
          "game_time": "7:15 PM ET",
          "away_team": "New York Mets",
          "home_team": "Arizona Diamondbacks",
          "away_pct": 0.395,
          "home_pct": 0.459,
          "away_prob": 0.4142,
          "home_prob": 0.5858,
          "pick": "Arizona Diamondbacks",
          "confidence": 0.5858,
          "actual_winner": "Arizona Diamondbacks",
          "correct": true
        },
        {
          "game_time": "7:15 PM ET",
          "away_team": "St. Louis Cardinals",
          "home_team": "San Diego Padres",
          "away_pct": 0.605,
          "home_pct": 0.579,
          "away_prob": 0.5072,
          "home_prob": 0.4928,
          "pick": "St. Louis Cardinals",
          "confidence": 0.5072,
          "actual_winner": "San Diego Padres",
          "correct": false
        },
        {
          "game_time": "9:05 PM ET",
          "away_team": "Pittsburgh Pirates",
          "home_team": "San Francisco Giants",
          "away_pct": 0.538,
          "home_pct": 0.395,
          "away_prob": 0.6214,
          "home_prob": 0.3786,
          "pick": "Pittsburgh Pirates",
          "confidence": 0.6214,
          "actual_winner": "Pittsburgh Pirates",
          "correct": true
        },
        {
          "game_time": "9:10 PM ET",
          "away_team": "Atlanta Braves",
          "home_team": "Los Angeles Dodgers",
          "away_pct": 0.667,
          "home_pct": 0.632,
          "away_prob": 0.5185,
          "home_prob": 0.4815,
          "pick": "Atlanta Braves",
          "confidence": 0.5185,
          "actual_winner": "Atlanta Braves",
          "correct": true
        },
        {
          "game_time": "4:10 PM ET",
          "away_team": "Tampa Bay Rays",
          "home_team": "Boston Red Sox",
          "away_pct": 0.658,
          "home_pct": 0.436,
          "away_prob": 0.6934,
          "home_prob": 0.3066,
          "pick": "Tampa Bay Rays",
          "confidence": 0.6934,
          "actual_winner": null,
          "correct": null
        }
      ]
    },
    {
      "date": "2026-05-03",
      "games": [
        {
          "game_time": "12:45 PM ET",
          "away_team": "Toronto Blue Jays",
          "home_team": "Minnesota Twins",
          "away_pct": 0.485,
          "home_pct": 0.412,
          "away_prob": 0.5735,
          "home_prob": 0.4265,
          "pick": "Toronto Blue Jays",
          "confidence": 0.5735,
          "actual_winner": null,
          "correct": null
        },
        {
          "game_time": "1:35 PM ET",
          "away_team": "Houston Astros",
          "home_team": "Boston Red Sox",
          "away_pct": 0.382,
          "home_pct": 0.394,
          "away_prob": 0.4878,
          "home_prob": 0.5122,
          "pick": "Boston Red Sox",
          "confidence": 0.5122,
          "actual_winner": null,
          "correct": null
        },
        {
          "game_time": "1:35 PM ET",
          "away_team": "Cincinnati Reds",
          "home_team": "Pittsburgh Pirates",
          "away_pct": 0.606,
          "home_pct": 0.529,
          "away_prob": 0.5776,
          "home_prob": 0.4224,
          "pick": "Cincinnati Reds",
          "confidence": 0.5776,
          "actual_winner": null,
          "correct": null
        },
        {
          "game_time": "1:35 PM ET",
          "away_team": "Baltimore Orioles",
          "home_team": "New York Yankees",
          "away_pct": 0.455,
          "home_pct": 0.667,
          "away_prob": 0.2941,
          "home_prob": 0.7059,
          "pick": "New York Yankees",
          "confidence": 0.7059,
          "actual_winner": null,
          "correct": null
        },
        {
          "game_time": "1:35 PM ET",
          "away_team": "Milwaukee Brewers",
          "home_team": "Washington Nationals",
          "away_pct": 0.562,
          "home_pct": 0.441,
          "away_prob": 0.6196,
          "home_prob": 0.3804,
          "pick": "Milwaukee Brewers",
          "confidence": 0.6196,
          "actual_winner": null,
          "correct": null
        },
        {
          "game_time": "1:40 PM ET",
          "away_team": "San Francisco Giants",
          "home_team": "Tampa Bay Rays",
          "away_pct": 0.394,
          "home_pct": 0.625,
          "away_prob": 0.2806,
          "home_prob": 0.7194,
          "pick": "Tampa Bay Rays",
          "confidence": 0.7194,
          "actual_winner": null,
          "correct": null
        },
        {
          "game_time": "1:40 PM ET",
          "away_team": "Philadelphia Phillies",
          "home_team": "Miami Marlins",
          "away_pct": 0.394,
          "home_pct": 0.485,
          "away_prob": 0.4085,
          "home_prob": 0.5915,
          "pick": "Miami Marlins",
          "confidence": 0.5915,
          "actual_winner": null,
          "correct": null
        },
        {
          "game_time": "2:15 PM ET",
          "away_team": "Los Angeles Dodgers",
          "home_team": "St. Louis Cardinals",
          "away_pct": 0.606,
          "home_pct": 0.606,
          "away_prob": 0.5,
          "home_prob": 0.5,
          "pick": "Los Angeles Dodgers",
          "confidence": 0.5,
          "actual_winner": null,
          "correct": null
        },
        {
          "game_time": "2:20 PM ET",
          "away_team": "Arizona Diamondbacks",
          "home_team": "Chicago Cubs",
          "away_pct": 0.5,
          "home_pct": 0.636,
          "away_prob": 0.3636,
          "home_prob": 0.6364,
          "pick": "Chicago Cubs",
          "confidence": 0.6364,
          "actual_winner": null,
          "correct": null
        },
        {
          "game_time": "3:10 PM ET",
          "away_team": "Atlanta Braves",
          "home_team": "Colorado Rockies",
          "away_pct": 0.706,
          "home_pct": 0.412,
          "away_prob": 0.7742,
          "home_prob": 0.2258,
          "pick": "Atlanta Braves",
          "confidence": 0.7742,
          "actual_winner": null,
          "correct": null
        },
        {
          "game_time": "4:05 PM ET",
          "away_team": "Cleveland Guardians",
          "home_team": "Athletics",
          "away_pct": 0.529,
          "home_pct": 0.515,
          "away_prob": 0.5143,
          "home_prob": 0.4857,
          "pick": "Cleveland Guardians",
          "confidence": 0.5143,
          "actual_winner": null,
          "correct": null
        },
        {
          "game_time": "4:07 PM ET",
          "away_team": "New York Mets",
          "home_team": "Los Angeles Angels",
          "away_pct": 0.333,
          "home_pct": 0.382,
          "away_prob": 0.4468,
          "home_prob": 0.5532,
          "pick": "Los Angeles Angels",
          "confidence": 0.5532,
          "actual_winner": null,
          "correct": null
        },
        {
          "game_time": "4:10 PM ET",
          "away_team": "Kansas City Royals",
          "home_team": "Seattle Mariners",
          "away_pct": 0.424,
          "home_pct": 0.471,
          "away_prob": 0.4532,
          "home_prob": 0.5468,
          "pick": "Seattle Mariners",
          "confidence": 0.5468,
          "actual_winner": null,
          "correct": null
        },
        {
          "game_time": "4:10 PM ET",
          "away_team": "Chicago White Sox",
          "home_team": "San Diego Padres",
          "away_pct": 0.485,
          "home_pct": 0.594,
          "away_prob": 0.3917,
          "home_prob": 0.6083,
          "pick": "San Diego Padres",
          "confidence": 0.6083,
          "actual_winner": null,
          "correct": null
        },
        {
          "game_time": "7:20 PM ET",
          "away_team": "Texas Rangers",
          "home_team": "Detroit Tigers",
          "away_pct": 0.485,
          "home_pct": 0.5,
          "away_prob": 0.4848,
          "home_prob": 0.5152,
          "pick": "Detroit Tigers",
          "confidence": 0.5152,
          "actual_winner": null,
          "correct": null
        }
      ]
    }
  ]
}